pysingletonmeta
