Metadata-Version: 2.4
Name: PySingletonMeta
Version: 0.1.0.3
Summary: Singleton Metaclass for comfy imports
Home-page: https://github.com/a-jean-andreasian/Lambda-REST-Client
Author: Armen-Jean Andreasian
Author-email: armen.andreasian.dev@proton.me
Classifier: Programming Language :: Python :: 3
Classifier: Operating System :: OS Independent
Requires-Python: >=3.8
License-File: LICENSE
Dynamic: author
Dynamic: author-email
Dynamic: classifier
Dynamic: description
Dynamic: description-content-type
Dynamic: home-page
Dynamic: license-file
Dynamic: requires-python
Dynamic: summary
